{"num_found":1,"time":0.000757623,"results":[{"mulu":[{"title":"1 大三昧金剛真實理儀軌分","file":"T08n0244","juan":1,"lb":"0786b22","type":"品","n":1},{"title":"2 一切如來真實理金剛三昧儀軌分","file":"T08n0244","juan":1,"lb":"0789b21","type":"品","n":2},{"title":"3 降伏三界金剛三昧大儀軌分","file":"T08n0244","juan":2,"lb":"0790b07","type":"品","n":3},{"title":"4 清淨諸煩惱三昧大儀軌分","file":"T08n0244","juan":2,"lb":"0791c12","type":"品","n":4},{"title":"5 一切寶灌頂大三昧儀軌分","file":"T08n0244","juan":2,"lb":"0792b12","type":"品","n":5},{"title":"6 一切拳印三昧大儀軌分","file":"T08n0244","juan":2,"lb":"0792c23","type":"品","n":6},{"title":"7 金剛字輪三昧大儀軌分","file":"T08n0244","juan":2,"lb":"0793c26","type":"品","n":7},{"title":"8 一切曼拏羅金剛輪三昧大儀軌分","file":"T08n0244","juan":2,"lb":"0794b10","type":"品","n":8},{"title":"9 眾金剛三昧大儀軌分","file":"T08n0244","juan":2,"lb":"0794c16","type":"品","n":9},{"title":"10 金剛忿怒三昧大儀軌分","file":"T08n0244","juan":2,"lb":"0795a26","type":"品","n":10},{"title":"11 一切樂三昧大儀軌分","file":"T08n0244","juan":3,"lb":"0795c19","type":"品","n":11},{"title":"12 外金剛部儀軌分","file":"T08n0244","juan":3,"lb":"0796a14","type":"品","n":12},{"title":"13 般若波羅蜜多教稱讚分","file":"T08n0244","juan":3,"lb":"0797a29","type":"品","n":13},{"title":"14 金剛手菩薩最上祕密大曼拏羅儀軌分","file":"T08n0244","juan":3,"lb":"0797b22","type":"品","n":14},{"title":"15 大樂金剛不空三昧大明印相成就儀軌分","file":"T08n0244","juan":4,"lb":"0802a12","type":"品","n":15},{"title":"16 一切如來金剛菩提大儀軌分","file":"T08n0244","juan":4,"lb":"0804a18","type":"品","n":16},{"title":"17 大金剛火焰日輪儀軌分","file":"T08n0244","juan":4,"lb":"0805b18","type":"品","n":17},{"title":"18 除諸業障一切智金剛儀軌分","file":"T08n0244","juan":5,"lb":"0807c23","type":"品","n":18},{"title":"19 圓滿一切願金剛寶儀軌分","file":"T08n0244","juan":5,"lb":"0809a17","type":"品","n":19},{"title":"20 一切儀軌中最上成就儀軌分","file":"T08n0244","juan":5,"lb":"0810a11","type":"品","n":20},{"title":"21 一切相應諸佛三昧曼拏羅儀軌分","file":"T08n0244","juan":5,"lb":"0811b26","type":"品","n":21},{"title":"22 一切如來大三昧曼拏羅儀軌分","file":"T08n0244","juan":6,"lb":"0814b08","type":"品","n":22},{"title":"23 一切相應儀軌分","file":"T08n0244","juan":6,"lb":"0817a21","type":"品","n":23},{"title":"24 最上成就印相分","file":"T08n0244","juan":7,"lb":"0819c08","type":"品","n":24},{"title":"25 最上祕密儀軌分","file":"T08n0244","juan":7,"lb":"0821c15","type":"品","n":25}],"juan":[{"file":"T08n0244","juan":1,"lb":"0786b18","title":"第一"},{"file":"T08n0244","juan":2,"lb":"0790b02","title":"第二"},{"file":"T08n0244","juan":3,"lb":"0795c14","title":"第三"},{"file":"T08n0244","juan":4,"lb":"0802a07","title":"第四"},{"file":"T08n0244","juan":5,"lb":"0807c19","title":"第五"},{"file":"T08n0244","juan":6,"lb":"0814b03","title":"第六"},{"file":"T08n0244","juan":7,"lb":"0819c03","title":"第七"}]}]}