{"num_found":1,"time":0.000900634,"results":[{"mulu":[{"title":"釋序品","file":"T34n1719","juan":1,"lb":"0151a06","type":"品","isFolder":true,"children":[{"title":"1","file":"T34n1719","juan":1,"lb":"0151a06","n":1},{"title":"2","file":"T34n1719","juan":2,"lb":"0172b02","n":2},{"title":"3","file":"T34n1719","juan":3,"lb":"0194a24","n":3}]},{"title":"釋方便品","file":"T34n1719","juan":3,"lb":"0209b25","type":"品","isFolder":true,"children":[{"title":"1","file":"T34n1719","juan":3,"lb":"0209b25","n":1},{"title":"2","file":"T34n1719","juan":4,"lb":"0215a07","n":2},{"title":"3","file":"T34n1719","juan":5,"lb":"0234c18","n":3}]},{"title":"釋譬喻品","file":"T34n1719","juan":5,"lb":"0253a02","type":"品","isFolder":true,"children":[{"title":"1","file":"T34n1719","juan":5,"lb":"0253a02","n":1},{"title":"2","file":"T34n1719","juan":6,"lb":"0255c04","n":2}]},{"title":"釋信解品","file":"T34n1719","juan":7,"lb":"0274b14","type":"品"},{"title":"釋藥草喻品","file":"T34n1719","juan":7,"lb":"0287c05","type":"品"},{"title":"釋授記品","file":"T34n1719","juan":8,"lb":"0295c08","type":"品"},{"title":"釋化城喻品","file":"T34n1719","juan":8,"lb":"0296c06","type":"品"},{"title":"釋五百弟子受記品","file":"T34n1719","juan":8,"lb":"0302c22","type":"品"},{"title":"釋受學無學人記品","file":"T34n1719","juan":8,"lb":"0304a13","type":"品"},{"title":"釋法師品","file":"T34n1719","juan":8,"lb":"0304b05","type":"品"},{"title":"釋見寶塔品","file":"T34n1719","juan":8,"lb":"0309c28","type":"品"},{"title":"釋提婆達多品","file":"T34n1719","juan":8,"lb":"0312b14","type":"品"},{"title":"釋持品","file":"T34n1719","juan":8,"lb":"0314c08","type":"品"},{"title":"釋安樂行品","file":"T34n1719","juan":9,"lb":"0316a24","type":"品"},{"title":"釋踊出品","file":"T34n1719","juan":9,"lb":"0323b05","type":"品"},{"title":"釋壽量品","file":"T34n1719","juan":9,"lb":"0327b23","type":"品","isFolder":true,"children":[{"title":"1","file":"T34n1719","juan":9,"lb":"0327b23","n":1},{"title":"2","file":"T34n1719","juan":10,"lb":"0337b27","n":2}]},{"title":"釋分別功德品","file":"T34n1719","juan":10,"lb":"0340c21","type":"品"},{"title":"釋隨喜功德品","file":"T34n1719","juan":10,"lb":"0344a07","type":"品"},{"title":"釋法師功德品","file":"T34n1719","juan":10,"lb":"0346a06","type":"品"},{"title":"釋常不輕菩薩品","file":"T34n1719","juan":10,"lb":"0347c08","type":"品"},{"title":"釋如來神力品","file":"T34n1719","juan":10,"lb":"0349c16","type":"品"},{"title":"釋囑累品","file":"T34n1719","juan":10,"lb":"0350b21","type":"品"},{"title":"釋藥王品","file":"T34n1719","juan":10,"lb":"0354a22","type":"品"},{"title":"釋妙音菩薩品","file":"T34n1719","juan":10,"lb":"0355b15","type":"品"},{"title":"釋普門品","file":"T34n1719","juan":10,"lb":"0356b18","type":"品"},{"title":"釋陀羅尼品","file":"T34n1719","juan":10,"lb":"0358a07","type":"品"},{"title":"釋嚴王品","file":"T34n1719","juan":10,"lb":"0358b12","type":"品"},{"title":"釋普賢品","file":"T34n1719","juan":10,"lb":"0359a03","type":"品"}],"juan":[{"file":"T34n1719","juan":1,"lb":"0151a03","title":"第一上"},{"file":"T34n1719","juan":1,"lb":"0158a02","title":"第一中"},{"file":"T34n1719","juan":1,"lb":"0165a21","title":"第一下"},{"file":"T34n1719","juan":2,"lb":"0172b02","title":"第二上"},{"file":"T34n1719","juan":2,"lb":"0179a26","title":"第二中"},{"file":"T34n1719","juan":2,"lb":"0185c10","title":"第二下"},{"file":"T34n1719","juan":3,"lb":"0194a24","title":"第三上"},{"file":"T34n1719","juan":3,"lb":"0200c02","title":"第三中"},{"file":"T34n1719","juan":3,"lb":"0209b22","title":"第三下"},{"file":"T34n1719","juan":4,"lb":"0215a07","title":"第四上"},{"file":"T34n1719","juan":4,"lb":"0222a17","title":"第四中"},{"file":"T34n1719","juan":4,"lb":"0228a19","title":"第四下"},{"file":"T34n1719","juan":5,"lb":"0234c18","title":"第五上"},{"file":"T34n1719","juan":5,"lb":"0240c11","title":"第五中"},{"file":"T34n1719","juan":5,"lb":"0247c02","title":"第五下"},{"file":"T34n1719","juan":6,"lb":"0255c04","title":"第六上"},{"file":"T34n1719","juan":6,"lb":"0262a02","title":"第六中"},{"file":"T34n1719","juan":6,"lb":"0267c22","title":"第六下"},{"file":"T34n1719","juan":7,"lb":"0274b11","title":"第七上"},{"file":"T34n1719","juan":7,"lb":"0281a12","title":"第七中"},{"file":"T34n1719","juan":7,"lb":"0287c02","title":"第七下"},{"file":"T34n1719","juan":8,"lb":"0295c05","title":"第八之一"},{"file":"T34n1719","juan":8,"lb":"0302c19","title":"第八之二"},{"file":"T34n1719","juan":8,"lb":"0304b02","title":"第八之三"},{"file":"T34n1719","juan":8,"lb":"0309c25","title":"第八之四"},{"file":"T34n1719","juan":9,"lb":"0316a21","title":"第九上"},{"file":"T34n1719","juan":9,"lb":"0323b02","title":"第九中"},{"file":"T34n1719","juan":9,"lb":"0330a26","title":"第九下"},{"file":"T34n1719","juan":10,"lb":"0337b24","title":"第十上"},{"file":"T34n1719","juan":10,"lb":"0344a04","title":"第十中"},{"file":"T34n1719","juan":10,"lb":"0350b18","title":"第十下"}]}]}