{"num_found":1,"time":0.00236539,"results":[{"mulu":[{"title":"1 部類增減","file":"T51n2068","juan":1,"lb":"0049a04","type":"其他","n":1},{"title":"2 隱顯時異","file":"T51n2068","juan":1,"lb":"0049c07","type":"其他","n":2},{"title":"3 傳譯年代","file":"T51n2068","juan":1,"lb":"0050c02","type":"其他","n":3},{"title":"4 支派別行","file":"T51n2068","juan":1,"lb":"0052b13","type":"其他","n":4},{"title":"5 論釋不同","file":"T51n2068","juan":1,"lb":"0052c24","type":"其他","n":5},{"title":"6 諸師序集","file":"T51n2068","juan":2,"lb":"0053a27","type":"其他","n":6,"isFolder":true,"children":[{"title":"1 法華宗要序","file":"T51n2068","juan":2,"lb":"0053b03","type":"其他","n":1},{"title":"2 法華經後序","file":"T51n2068","juan":2,"lb":"0053c16","type":"其他","n":2},{"title":"3 法華經序","file":"T51n2068","juan":2,"lb":"0054a19","type":"其他","n":3},{"title":"4 法華翻經後記","file":"T51n2068","juan":2,"lb":"0054a24","type":"其他","n":4},{"title":"5 添品法華序","file":"T51n2068","juan":2,"lb":"0054b19","type":"其他","n":5},{"title":"6 無量義經序","file":"T51n2068","juan":2,"lb":"0054c15","type":"其他","n":6},{"title":"7 正法華經記","file":"T51n2068","juan":2,"lb":"0055b26","type":"其他","n":7}]},{"title":"7 講解感應","file":"T51n2068","juan":2,"lb":"0055c07","type":"其他","n":7,"isFolder":true,"children":[{"title":"之一","file":"T51n2068","juan":2,"lb":"0055c07","type":"其他","isFolder":true,"children":[{"title":"1 晉長安釋僧叡","file":"T51n2068","juan":2,"lb":"0055c13","type":"其他","n":1},{"title":"2 晉京師龍光寺釋道生","file":"T51n2068","juan":2,"lb":"0056a08","type":"其他","n":2},{"title":"3 宋吳虎丘釋曇諦","file":"T51n2068","juan":2,"lb":"0056a16","type":"其他","n":3},{"title":"4 宋壽春名閻寺釋僧導","file":"T51n2068","juan":2,"lb":"0056a25","type":"其他","n":4},{"title":"5 齊京師中興寺釋僧印","file":"T51n2068","juan":2,"lb":"0056b04","type":"其他","n":5},{"title":"6 梁揚都光宅寺釋法雲","file":"T51n2068","juan":2,"lb":"0056b12","type":"其他","n":6},{"title":"7 梁滿法師","file":"T51n2068","juan":2,"lb":"0056c07","type":"其他","n":7},{"title":"8 隋國師智者天台國清寺釋智顗","file":"T51n2068","juan":2,"lb":"0056c14","type":"其他","n":8},{"title":"9 唐京師延興寺釋吉藏","file":"T51n2068","juan":2,"lb":"0057a15","type":"其他","n":9}]},{"title":"之二","file":"T51n2068","juan":3,"lb":"0057b15","type":"其他","isFolder":true,"children":[{"title":"1 唐國清寺釋灌頂","file":"T51n2068","juan":3,"lb":"0057b15","type":"其他","n":1},{"title":"2 唐京城真寂寺釋慧如","file":"T51n2068","juan":3,"lb":"0057c01","type":"其他","n":2},{"title":"3 釋僧隆法師","file":"T51n2068","juan":3,"lb":"0057c24","type":"其他","n":3},{"title":"4 唐大慈恩寺釋窺基","file":"T51n2068","juan":3,"lb":"0058a12","type":"其他","n":4},{"title":"5 唐左溪釋玄朗","file":"T51n2068","juan":3,"lb":"0058a29","type":"其他","n":5},{"title":"6 唐釋慧明","file":"T51n2068","juan":3,"lb":"0058b14","type":"其他","n":6},{"title":"7 唐釋智因","file":"T51n2068","juan":3,"lb":"0058c10","type":"其他","n":7},{"title":"8 唐釋志實","file":"T51n2068","juan":3,"lb":"0058c22","type":"其他","n":8},{"title":"9 相州釋道昂","file":"T51n2068","juan":3,"lb":"0059a06","type":"其他","n":9},{"title":"10 江南釋志遠","file":"T51n2068","juan":3,"lb":"0059a12","type":"其他","n":10}]}]},{"title":"8 諷誦勝利","file":"T51n2068","juan":3,"lb":"0059a21","type":"其他","n":8,"isFolder":true,"children":[{"title":"之一","file":"T51n2068","juan":3,"lb":"0059a21","type":"其他","isFolder":true,"children":[{"title":"1 陳南岳衡山釋慧思","file":"T51n2068","juan":3,"lb":"0059a29","type":"其他","n":1},{"title":"2 陳國師南岳大善","file":"T51n2068","juan":3,"lb":"0059b14","type":"其他","n":2},{"title":"3 隋天台山國清寺釋智越","file":"T51n2068","juan":3,"lb":"0059b18","type":"其他","n":3},{"title":"4 隋河東栖巖道場釋智通","file":"T51n2068","juan":3,"lb":"0059c19","type":"其他","n":4},{"title":"5 唐台州國清寺釋智晞","file":"T51n2068","juan":3,"lb":"0060a18","type":"其他","n":5},{"title":"6 唐天台山國清寺釋智璪","file":"T51n2068","juan":3,"lb":"0060c22","type":"其他","n":6},{"title":"7 唐雍州津梁寺釋法喜","file":"T51n2068","juan":3,"lb":"0061b15","type":"其他","n":7},{"title":"8 陳宣帝師江陵慧誠","file":"T51n2068","juan":3,"lb":"0061c15","type":"其他","n":8},{"title":"9 唐南雲峯慧勇","file":"T51n2068","juan":3,"lb":"0061c18","type":"其他","n":9},{"title":"10 隋國師南岳慧稠","file":"T51n2068","juan":3,"lb":"0061c21","type":"其他","n":10},{"title":"11 隋新羅緣光","file":"T51n2068","juan":3,"lb":"0061c24","type":"其他","n":11},{"title":"12 唐終南山悟真寺善義","file":"T51n2068","juan":3,"lb":"0061c27","type":"其他","n":12},{"title":"13 唐富陽玉泉寺弘景","file":"T51n2068","juan":3,"lb":"0062a01","type":"其他","n":13}]},{"title":"之二","file":"T51n2068","juan":4,"lb":"0062a09","type":"其他","isFolder":true,"children":[{"title":"1 晉阿陰白馬寺釋曇邃","file":"T51n2068","juan":4,"lb":"0062a25","type":"其他","n":1},{"title":"2 晉山陰顯義寺竺法純","file":"T51n2068","juan":4,"lb":"0062b08","type":"其他","n":2},{"title":"3 晉蜀三賢寺釋僧生","file":"T51n2068","juan":4,"lb":"0062b16","type":"其他","n":3},{"title":"4 宋剡法華臺釋法宗","file":"T51n2068","juan":4,"lb":"0062b26","type":"其他","n":4},{"title":"5 宋京師南㵎寺釋道冏","file":"T51n2068","juan":4,"lb":"0062c08","type":"其他","n":5},{"title":"6 宋廬山釋慧慶","file":"T51n2068","juan":4,"lb":"0062c29","type":"其他","n":6},{"title":"7 宋臨淄釋普明","file":"T51n2068","juan":4,"lb":"0063a10","type":"其他","n":7},{"title":"8 宋京師道場寺釋法莊","file":"T51n2068","juan":4,"lb":"0063a20","type":"其他","n":8},{"title":"9 宋京師東瓦官寺釋慧果","file":"T51n2068","juan":4,"lb":"0063a28","type":"其他","n":9},{"title":"10 齊京師高座寺釋慧進","file":"T51n2068","juan":4,"lb":"0063b09","type":"其他","n":10},{"title":"11 齊永興柏林寺釋弘明","file":"T51n2068","juan":4,"lb":"0063b22","type":"其他","n":11},{"title":"12 齊京師靈根寺釋慧豫","file":"T51n2068","juan":4,"lb":"0063c06","type":"其他","n":12},{"title":"13 齊上定林釋超辯","file":"T51n2068","juan":4,"lb":"0063c16","type":"其他","n":13},{"title":"14 齊山陰天柱寺釋法慧","file":"T51n2068","juan":4,"lb":"0063c26","type":"其他","n":14},{"title":"15 齊京師後崗釋僧侯","file":"T51n2068","juan":4,"lb":"0064a05","type":"其他","n":15},{"title":"16 魏泰岳人頭山草寺釋志湛","file":"T51n2068","juan":4,"lb":"0064a15","type":"其他","n":16},{"title":"17 范陽五侯寺僧","file":"T51n2068","juan":4,"lb":"0064a27","type":"其他","n":17},{"title":"18 雍州僧法常","file":"T51n2068","juan":4,"lb":"0064b03","type":"其他","n":18},{"title":"19 齊并州誦經舌","file":"T51n2068","juan":4,"lb":"0064b09","type":"其他","n":19},{"title":"20 唐終南山藍谷悟真寺釋慧超","file":"T51n2068","juan":4,"lb":"0064b23","type":"其他","n":20},{"title":"21 百濟國達拏山寺釋慧顯","file":"T51n2068","juan":4,"lb":"0064c22","type":"其他","n":21},{"title":"22 唐驪山津梁寺釋善慧","file":"T51n2068","juan":4,"lb":"0065a05","type":"其他","n":22},{"title":"23 晉大原沙門釋慧達","file":"T51n2068","juan":4,"lb":"0065b06","type":"其他","n":23},{"title":"24 唐終南山悟真寺釋法誠","file":"T51n2068","juan":4,"lb":"0065b14","type":"其他","n":24},{"title":"25 唐京師大莊嚴寺釋慧銓","file":"T51n2068","juan":4,"lb":"0065c19","type":"其他","n":25},{"title":"26 宋黃龍沙彌曇無竭","file":"T51n2068","juan":4,"lb":"0066a13","type":"其他","n":26},{"title":"27 晉蜀石室山釋法緒","file":"T51n2068","juan":4,"lb":"0066a23","type":"其他","n":27},{"title":"28 宋山陰法華山釋僧翼","file":"T51n2068","juan":4,"lb":"0066b01","type":"其他","n":28},{"title":"29 唐潤州攝山栖霞寺釋智聰","file":"T51n2068","juan":4,"lb":"0066b13","type":"其他","n":29},{"title":"30 隋京師靜法寺釋智嶷","file":"T51n2068","juan":4,"lb":"0066c05","type":"其他","n":30}]},{"title":"之三","file":"T51n2068","juan":5,"lb":"0066c22","type":"其他","isFolder":true,"children":[{"title":"1 雍州醴泉沙門釋遺俗","file":"T51n2068","juan":5,"lb":"0067a07","type":"其他","n":1},{"title":"2 雍州福水陰史村呵誓","file":"T51n2068","juan":5,"lb":"0067a21","type":"其他","n":2},{"title":"3 黃州隨華寺僧玄秀","file":"T51n2068","juan":5,"lb":"0067b02","type":"其他","n":3},{"title":"4 唐益州福成寺僧道慧","file":"T51n2068","juan":5,"lb":"0067b11","type":"其他","n":4},{"title":"5 魏常山衡唐精舍釋道泰","file":"T51n2068","juan":5,"lb":"0067b21","type":"其他","n":5},{"title":"6 陳揚都釋普安","file":"T51n2068","juan":5,"lb":"0067c04","type":"其他","n":6},{"title":"7 唐潞州法住寺釋僧定","file":"T51n2068","juan":5,"lb":"0067c17","type":"其他","n":7},{"title":"8 隋岐州東山下村沙彌","file":"T51n2068","juan":5,"lb":"0068a04","type":"其他","n":8},{"title":"9 縫州陷泉寺釋僧徹","file":"T51n2068","juan":5,"lb":"0068a17","type":"其他","n":9},{"title":"10 唐并州釋僧衍","file":"T51n2068","juan":5,"lb":"0068a24","type":"其他","n":10},{"title":"11 中書令岑文","file":"T51n2068","juan":5,"lb":"0068b16","type":"其他","n":11},{"title":"12 國子祭酒肅璟","file":"T51n2068","juan":5,"lb":"0068b25","type":"其他","n":12},{"title":"13 臨邛韋仲珪","file":"T51n2068","juan":5,"lb":"0068c22","type":"其他","n":13},{"title":"14 唐金城瓦官寺釋慧獻","file":"T51n2068","juan":5,"lb":"0069a08","type":"其他","n":14},{"title":"15 都下眾造寺慧和","file":"T51n2068","juan":5,"lb":"0069a20","type":"其他","n":15},{"title":"16 司亢少常伯崔義起","file":"T51n2068","juan":5,"lb":"0069a27","type":"其他","n":16},{"title":"17 山陽蓋護","file":"T51n2068","juan":5,"lb":"0069b24","type":"其他","n":17},{"title":"18 秦州慕容文策","file":"T51n2068","juan":5,"lb":"0069c01","type":"其他","n":18},{"title":"19 宋法華臺沙彌","file":"T51n2068","juan":5,"lb":"0070a24","type":"其他","n":19},{"title":"20 天水隴城志通","file":"T51n2068","juan":5,"lb":"0070b18","type":"其他","n":20},{"title":"21 涼州寡婦","file":"T51n2068","juan":5,"lb":"0071a16","type":"其他","n":21},{"title":"22 隋并州高守節","file":"T51n2068","juan":5,"lb":"0071a26","type":"其他","n":22},{"title":"23 昭果寺釋明曜","file":"T51n2068","juan":5,"lb":"0071b28","type":"其他","n":23},{"title":"24 瓦官寺釋僧洪","file":"T51n2068","juan":5,"lb":"0071c13","type":"其他","n":24},{"title":"25 大原王珠","file":"T51n2068","juan":5,"lb":"0071c27","type":"其他","n":25}]},{"title":"之四","file":"T51n2068","juan":6,"lb":"0072a15","type":"其他","isFolder":true,"children":[{"title":"1 越州觀音道場道人","file":"T51n2068","juan":6,"lb":"0072a28","type":"其他","n":1},{"title":"2 河東薰雄","file":"T51n2068","juan":6,"lb":"0072c04","type":"其他","n":2},{"title":"3 唐溜州釋通慧","file":"T51n2068","juan":6,"lb":"0073a03","type":"其他","n":3},{"title":"4 隋開善寺沙彌","file":"T51n2068","juan":6,"lb":"0073a18","type":"其他","n":4},{"title":"5 沙呵羅國西耳福緣","file":"T51n2068","juan":6,"lb":"0073b06","type":"其他","n":5},{"title":"6 宋益陽彭子喬","file":"T51n2068","juan":6,"lb":"0073b22","type":"其他","n":6},{"title":"7 青州白苟寺釋慧勝","file":"T51n2068","juan":6,"lb":"0073c09","type":"其他","n":7},{"title":"8宣州尼法空","file":"T51n2068","juan":6,"lb":"0073c14","type":"其他","n":8},{"title":"9 代州總因寺釋妙蓮","file":"T51n2068","juan":6,"lb":"0074a04","type":"其他","n":9},{"title":"10 唐真寂寺釋慧生","file":"T51n2068","juan":6,"lb":"0074a26","type":"其他","n":10},{"title":"11 并州釋曇義","file":"T51n2068","juan":6,"lb":"0074c18","type":"其他","n":11},{"title":"12 齊州三總山釋清慧","file":"T51n2068","juan":6,"lb":"0074c28","type":"其他","n":12},{"title":"13 建德郡王穀","file":"T51n2068","juan":6,"lb":"0075a28","type":"其他","n":13},{"title":"14 長安大寺比丘尼妙法","file":"T51n2068","juan":6,"lb":"0075b04","type":"其他","n":14},{"title":"15 唐洛州虞林通","file":"T51n2068","juan":6,"lb":"0075b18","type":"其他","n":15},{"title":"16 左監門挍尉憑翊李山龍","file":"T51n2068","juan":6,"lb":"0075c03","type":"其他","n":16},{"title":"17 龜茲國沙門達磨跋陀","file":"T51n2068","juan":6,"lb":"0076a23","type":"其他","n":17},{"title":"18 金城釋僧智","file":"T51n2068","juan":6,"lb":"0076b09","type":"其他","n":18},{"title":"19 晉沙門釋慧達","file":"T51n2068","juan":6,"lb":"0076b16","type":"其他","n":19},{"title":"20 長安城寡女揚氏","file":"T51n2068","juan":6,"lb":"0076b25","type":"其他","n":20},{"title":"21 沙門釋法道","file":"T51n2068","juan":6,"lb":"0076c14","type":"其他","n":21},{"title":"22 隋相州北道僧","file":"T51n2068","juan":6,"lb":"0076c20","type":"其他","n":22},{"title":"23 唐西京勝業寺二僧","file":"T51n2068","juan":6,"lb":"0077a07","type":"其他","n":23},{"title":"24 晉竺長舒","file":"T51n2068","juan":6,"lb":"0077b03","type":"其他","n":24}]}]},{"title":"9 轉讀滅罪","file":"T51n2068","juan":7,"lb":"0077b24","type":"其他","n":9,"isFolder":true,"children":[{"title":"1 京師高表仁孫子","file":"T51n2068","juan":7,"lb":"0077c04","type":"其他","n":1},{"title":"2 蘇長安家妾","file":"T51n2068","juan":7,"lb":"0077c26","type":"其他","n":2},{"title":"3 隋魏州彥武","file":"T51n2068","juan":7,"lb":"0078a05","type":"其他","n":3},{"title":"4 彭城域人韓睦之","file":"T51n2068","juan":7,"lb":"0078a22","type":"其他","n":4},{"title":"5 隋鄜州寶室寺沙門淨藏","file":"T51n2068","juan":7,"lb":"0078b12","type":"其他","n":5},{"title":"6 梁蒙遜王","file":"T51n2068","juan":7,"lb":"0078b24","type":"其他","n":6},{"title":"7 隋豫州慧緣","file":"T51n2068","juan":7,"lb":"0078c05","type":"其他","n":7},{"title":"8 梁九江東林寺僧融","file":"T51n2068","juan":7,"lb":"0079a02","type":"其他","n":8},{"title":"9 天竺阿蘭若比丘","file":"T51n2068","juan":7,"lb":"0079a14","type":"其他","n":9},{"title":"10 天竺于闐國瞿摩帝寺沙彌","file":"T51n2068","juan":7,"lb":"0079a25","type":"其他","n":10},{"title":"11 天竺𤘽薩羅國摩訶衍提婆","file":"T51n2068","juan":7,"lb":"0079b07","type":"其他","n":11},{"title":"12 隋揚州嚴敬","file":"T51n2068","juan":7,"lb":"0079b24","type":"其他","n":12},{"title":"13 安居縣樣女","file":"T51n2068","juan":7,"lb":"0079c06","type":"其他","n":13},{"title":"14 大原小女","file":"T51n2068","juan":7,"lb":"0079c12","type":"其他","n":14},{"title":"15 潯陽尼妙空","file":"T51n2068","juan":7,"lb":"0079c18","type":"其他","n":15},{"title":"16 隋并州高守節家女","file":"T51n2068","juan":7,"lb":"0079c24","type":"其他","n":16}]},{"title":"10 書寫救苦","file":"T51n2068","juan":7,"lb":"0080a01","type":"其他","n":10,"isFolder":true,"children":[{"title":"之一","file":"T51n2068","juan":7,"lb":"0080a01","type":"其他","isFolder":true,"children":[{"title":"1 秦姚興文皇帝","file":"T51n2068","juan":7,"lb":"0080a10","type":"其他","n":1},{"title":"2 天竺波羅奈國僧","file":"T51n2068","juan":7,"lb":"0080b02","type":"其他","n":2},{"title":"3 外國清信女","file":"T51n2068","juan":7,"lb":"0080b23","type":"其他","n":3},{"title":"4 竺曇遂同學僧","file":"T51n2068","juan":7,"lb":"0080c05","type":"其他","n":4},{"title":"5 齊青州道㑺","file":"T51n2068","juan":7,"lb":"0080c21","type":"其他","n":5},{"title":"6 唐濟州靈光寺沙彌","file":"T51n2068","juan":7,"lb":"0081a12","type":"其他","n":6},{"title":"7 越州結緣經","file":"T51n2068","juan":7,"lb":"0081a25","type":"其他","n":7},{"title":"8 宋釋法豐","file":"T51n2068","juan":7,"lb":"0081b15","type":"其他","n":8},{"title":"9 唐法海寺釋僧安","file":"T51n2068","juan":7,"lb":"0081b24","type":"其他","n":9},{"title":"10 唐定水寺釋智琰","file":"T51n2068","juan":7,"lb":"0081b29","type":"其他","n":10},{"title":"11 唐蒲州陷泉寺釋義徹","file":"T51n2068","juan":7,"lb":"0081c06","type":"其他","n":11},{"title":"12 唐綿州寡妾","file":"T51n2068","juan":7,"lb":"0081c13","type":"其他","n":12},{"title":"13 唐箕州司馬","file":"T51n2068","juan":7,"lb":"0081c19","type":"其他","n":13},{"title":"14 唐并州司馬楚宣宗","file":"T51n2068","juan":7,"lb":"0081c26","type":"其他","n":14},{"title":"15 唐陳氏","file":"T51n2068","juan":7,"lb":"0082a14","type":"其他","n":15},{"title":"16 唐溜州李健安","file":"T51n2068","juan":7,"lb":"0082b17","type":"其他","n":16}]},{"title":"之二","file":"T51n2068","juan":8,"lb":"0082c13","type":"其他","isFolder":true,"children":[{"title":"1 隋相州僧玄緒","file":"T51n2068","juan":8,"lb":"0082c23","type":"其他","n":1},{"title":"2 宋瓦官寺釋惠道","file":"T51n2068","juan":8,"lb":"0083a22","type":"其他","n":2},{"title":"3 定州曇韻","file":"T51n2068","juan":8,"lb":"0083b08","type":"其他","n":3},{"title":"4 隆州令孤元軌","file":"T51n2068","juan":8,"lb":"0083b23","type":"其他","n":4},{"title":"5 蔣州嚴恭","file":"T51n2068","juan":8,"lb":"0083c08","type":"其他","n":5},{"title":"6 并州李遺龍","file":"T51n2068","juan":8,"lb":"0083c26","type":"其他","n":6},{"title":"7 唐梓州姚待","file":"T51n2068","juan":8,"lb":"0084b04","type":"其他","n":7},{"title":"8 揚州高郵縣李丘令","file":"T51n2068","juan":8,"lb":"0085a16","type":"其他","n":8},{"title":"9 唐河東練行尼","file":"T51n2068","juan":8,"lb":"0085b18","type":"其他","n":9},{"title":"10 揚州嚴恭","file":"T51n2068","juan":8,"lb":"0085c03","type":"其他","n":10},{"title":"11 滿州虞縣不信男","file":"T51n2068","juan":8,"lb":"0086a13","type":"其他","n":11},{"title":"12 隋大業中客僧","file":"T51n2068","juan":8,"lb":"0086b06","type":"其他","n":12},{"title":"13 絳州孤山西河道場僧","file":"T51n2068","juan":8,"lb":"0086c05","type":"其他","n":13},{"title":"14 北齊仕人","file":"T51n2068","juan":8,"lb":"0087a03","type":"其他","n":14},{"title":"15 定州釋修德","file":"T51n2068","juan":8,"lb":"0087a25","type":"其他","n":15},{"title":"16 齊太祖高帝","file":"T51n2068","juan":8,"lb":"0087b17","type":"其他","n":16},{"title":"17 并州清信女","file":"T51n2068","juan":8,"lb":"0087c04","type":"其他","n":17},{"title":"18 唐襄州神足寺慧眺","file":"T51n2068","juan":8,"lb":"0087c12","type":"其他","n":18}]}]},{"title":"11 聽聞利益","file":"T51n2068","juan":9,"lb":"0088a05","type":"其他","n":11,"isFolder":true,"children":[{"title":"1 佛在世光明女","file":"T51n2068","juan":9,"lb":"0088a17","type":"其他","n":1},{"title":"2 佛在世妙意天子","file":"T51n2068","juan":9,"lb":"0088b01","type":"其他","n":2},{"title":"3 迦葉佛末法商主","file":"T51n2068","juan":9,"lb":"0088b09","type":"其他","n":3},{"title":"4 王舍城旃陀羅子","file":"T51n2068","juan":9,"lb":"0088b20","type":"其他","n":4},{"title":"5 貞觀鴿兒","file":"T51n2068","juan":9,"lb":"0088c26","type":"其他","n":5},{"title":"6 長安縣蔚範良子","file":"T51n2068","juan":9,"lb":"0089a10","type":"其他","n":6},{"title":"7 外國得通沙彌","file":"T51n2068","juan":9,"lb":"0089a25","type":"其他","n":7},{"title":"8 廣州法譽","file":"T51n2068","juan":9,"lb":"0089b17","type":"其他","n":8},{"title":"9 毒蛇生天","file":"T51n2068","juan":9,"lb":"0089c08","type":"其他","n":9},{"title":"10 舍衛城波斯匿伽羅王","file":"T51n2068","juan":9,"lb":"0090a02","type":"其他","n":10},{"title":"11 潯陽湖海女","file":"T51n2068","juan":9,"lb":"0090b20","type":"其他","n":11},{"title":"12 雍州醴泉縣沙彌","file":"T51n2068","juan":9,"lb":"0090c21","type":"其他","n":12},{"title":"13 南陽僧法朗猴犬","file":"T51n2068","juan":9,"lb":"0091a02","type":"其他","n":13},{"title":"14 魏常山衡唐精舍蝙蝠","file":"T51n2068","juan":9,"lb":"0091a27","type":"其他","n":14},{"title":"15 隋吳郡虎丘山獼猴","file":"T51n2068","juan":9,"lb":"0091b06","type":"其他","n":15},{"title":"16 月支蘇摩耶菩薩所見餓鬼","file":"T51n2068","juan":9,"lb":"0091b17","type":"其他","n":16},{"title":"17 潯陽處女","file":"T51n2068","juan":9,"lb":"0091c26","type":"其他","n":17},{"title":"18 西域毘末羅密多","file":"T51n2068","juan":9,"lb":"0092a10","type":"其他","n":18},{"title":"19 尼智通","file":"T51n2068","juan":9,"lb":"0092b04","type":"其他","n":19},{"title":"20 沙彌雲藏","file":"T51n2068","juan":9,"lb":"0092b13","type":"其他","n":20},{"title":"21 慈門寺僧孝慈","file":"T51n2068","juan":9,"lb":"0092b20","type":"其他","n":21},{"title":"22 唐襄州優婆塞後妻","file":"T51n2068","juan":9,"lb":"0092c13","type":"其他","n":22}]},{"title":"12 依正供養","file":"T51n2068","juan":10,"lb":"0093a05","type":"其他","n":12,"isFolder":true,"children":[{"title":"1 宋臨川招提寺釋慧紹","file":"T51n2068","juan":10,"lb":"0093a15","type":"其他","n":1},{"title":"2 宋京師竹林寺釋慧益","file":"T51n2068","juan":10,"lb":"0093b02","type":"其他","n":2},{"title":"3 齊隴西釋法光","file":"T51n2068","juan":10,"lb":"0093c02","type":"其他","n":3},{"title":"4 隋九江廬山沙門釋大志","file":"T51n2068","juan":10,"lb":"0093c10","type":"其他","n":4},{"title":"5 唐終南豹林谷釋會通","file":"T51n2068","juan":10,"lb":"0094a08","type":"其他","n":5},{"title":"6 荊州比丘尼","file":"T51n2068","juan":10,"lb":"0094a17","type":"其他","n":6},{"title":"7 并州城西書生","file":"T51n2068","juan":10,"lb":"0094a29","type":"其他","n":7},{"title":"8 宋廬山招提寺釋僧瑜","file":"T51n2068","juan":10,"lb":"0094b05","type":"其他","n":8},{"title":"9 十種供養記","file":"T51n2068","juan":10,"lb":"0094b28","type":"其他","n":9},{"title":"10 滅度受持供養經卷者彌勒出世時得益","file":"T51n2068","juan":10,"lb":"0095b02","type":"其他","n":10},{"title":"11 外國妙華天女","file":"T51n2068","juan":10,"lb":"0095b23","type":"其他","n":11},{"title":"12 忉利天寶瓔天子","file":"T51n2068","juan":10,"lb":"0095c09","type":"其他","n":12},{"title":"13 長安縣老女","file":"T51n2068","juan":10,"lb":"0095c22","type":"其他","n":13},{"title":"14 江寧縣優婆塞","file":"T51n2068","juan":10,"lb":"0096a09","type":"其他","n":14},{"title":"15 隋天台山瀑布寺釋僧達","file":"T51n2068","juan":10,"lb":"0096b03","type":"其他","n":15},{"title":"16 法供養勝","file":"T51n2068","juan":10,"lb":"0096b12","type":"其他","n":16},{"title":"17 無行比丘","file":"T51n2068","juan":10,"lb":"0096c13","type":"其他","n":17}]}],"juan":[{"file":"T51n2068","juan":1,"lb":"0048b21","title":"第一"},{"file":"T51n2068","juan":2,"lb":"0053a25","title":"第二"},{"file":"T51n2068","juan":3,"lb":"0057b06","title":"第三"},{"file":"T51n2068","juan":4,"lb":"0062a07","title":"第四"},{"file":"T51n2068","juan":5,"lb":"0066c20","title":"第五"},{"file":"T51n2068","juan":6,"lb":"0072a13","title":"第六"},{"file":"T51n2068","juan":7,"lb":"0077b22","title":"第七"},{"file":"T51n2068","juan":8,"lb":"0082c11","title":"第八"},{"file":"T51n2068","juan":9,"lb":"0088a03","title":"第九"},{"file":"T51n2068","juan":10,"lb":"0093a03","title":"第十"}]}]}