{"num_found":1,"time":0.00053792,"results":[{"mulu":[{"title":"1 十門分別(上)","file":"T42n1826","juan":1,"lb":"0212c05","type":"其他","n":1,"isFolder":true,"children":[{"title":"1 教起所因","file":"T42n1826","juan":1,"lb":"0212c09","type":"其他","n":1},{"title":"2 藏部所攝","file":"T42n1826","juan":1,"lb":"0212c25","type":"其他","n":2},{"title":"3 顯教分齊","file":"T42n1826","juan":1,"lb":"0213a04","type":"其他","n":3},{"title":"4 教所被機","file":"T42n1826","juan":1,"lb":"0213c24","type":"其他","n":4},{"title":"5 能詮教體","file":"T42n1826","juan":1,"lb":"0214a09","type":"其他","n":5},{"title":"6 所詮宗趣","file":"T42n1826","juan":1,"lb":"0214a16","type":"其他","n":6},{"title":"7 造論時代","file":"T42n1826","juan":1,"lb":"0218c12","type":"其他","n":7},{"title":"8 傳譯緣起","file":"T42n1826","juan":1,"lb":"0218c23","type":"其他","n":8},{"title":"9 釋論題目","file":"T42n1826","juan":1,"lb":"0219a03","type":"其他","n":9},{"title":"10 隨文解釋","file":"T42n1826","juan":1,"lb":"0219b19","type":"其他","n":10}]},{"title":"2 開宗解釋","file":"T42n1826","juan":1,"lb":"0220b05","type":"其他","n":2,"isFolder":true,"children":[{"title":"1 觀因緣門(上)","file":"T42n1826","juan":1,"lb":"0220b07","type":"其他","n":1},{"title":"2 觀有果無果門(下)","file":"T42n1826","juan":2,"lb":"0221b15","type":"其他","n":2},{"title":"3 觀緣門(下)","file":"T42n1826","juan":2,"lb":"0223c04","type":"其他","n":3},{"title":"4 觀相門(下)","file":"T42n1826","juan":2,"lb":"0224a21","type":"其他","n":4},{"title":"5 觀有相無相門(下)","file":"T42n1826","juan":2,"lb":"0225c25","type":"其他","n":5},{"title":"6 觀一異門(下)","file":"T42n1826","juan":2,"lb":"0226a18","type":"其他","n":6},{"title":"7 觀有無門(下)","file":"T42n1826","juan":2,"lb":"0226c24","type":"其他","n":7},{"title":"8 觀性門(下)","file":"T42n1826","juan":2,"lb":"0227b18","type":"其他","n":8},{"title":"9 觀因果門(下)","file":"T42n1826","juan":2,"lb":"0228a22","type":"其他","n":9},{"title":"10 觀作者門(下)","file":"T42n1826","juan":2,"lb":"0228b10","type":"其他","n":10},{"title":"11 觀三時門(下)","file":"T42n1826","juan":2,"lb":"0229c29","type":"其他","n":11},{"title":"12 觀生門(下)","file":"T42n1826","juan":2,"lb":"0230b28","type":"其他","n":12}]}],"juan":[{"file":"T42n1826","juan":1,"lb":"0212b14","title":"第一"},{"file":"T42n1826","juan":2,"lb":"0221b12","title":"第二"}]}]}