{"num_found":1,"time":0.000690618,"results":[{"mulu":[{"title":"1 初發意悅豫住品","file":"T10n0285","juan":1,"lb":"0458a20","type":"品","n":1},{"title":"2 離垢住品","file":"T10n0285","juan":1,"lb":"0465c04","type":"品","n":2},{"title":"3 興光住品","file":"T10n0285","juan":2,"lb":"0468b24","type":"品","n":3},{"title":"4 暉曜住品","file":"T10n0285","juan":2,"lb":"0471a15","type":"品","n":4},{"title":"5 難勝住品","file":"T10n0285","juan":3,"lb":"0473a27","type":"品","n":5},{"title":"6 目前住品","file":"T10n0285","juan":3,"lb":"0475c21","type":"品","n":6},{"title":"7 玄妙住品","file":"T10n0285","juan":4,"lb":"0478c26","type":"品","n":7},{"title":"8 不動住品","file":"T10n0285","juan":4,"lb":"0482b02","type":"品","n":8},{"title":"9 善哉意住品","file":"T10n0285","juan":4,"lb":"0485c26","type":"品","n":9},{"title":"10 金剛藏問菩薩住品","file":"T10n0285","juan":5,"lb":"0490a05","type":"品","n":10}],"juan":[{"file":"T10n0285","juan":1,"lb":"0458a16","title":"第一"},{"file":"T10n0285","juan":2,"lb":"0468b21","title":"第二"},{"file":"T10n0285","juan":3,"lb":"0473a24","title":"第三"},{"file":"T10n0285","juan":4,"lb":"0478c23","title":"第四"},{"file":"T10n0285","juan":5,"lb":"0490a02","title":"第五"}]}]}