{"num_found":1,"time":0.00052668,"results":[{"mulu":[{"title":"1 阿吒婆拘請賢聖法","file":"T21n1238","juan":1,"lb":"0182a19","type":"其他","n":1,"isFolder":true,"children":[{"title":"1 請十方諸佛印","file":"T21n1238","juan":1,"lb":"0182a20","type":"其他","n":1},{"title":"2 請觀世音菩薩印","file":"T21n1238","juan":1,"lb":"0182a25","type":"其他","n":2},{"title":"3 喚集十四都金剛印","file":"T21n1238","juan":1,"lb":"0182a29","type":"其他","n":3},{"title":"4 集三十三天神印","file":"T21n1238","juan":1,"lb":"0182b05","type":"其他","n":4},{"title":"5 集二十八宿星天印","file":"T21n1238","juan":1,"lb":"0182b10","type":"其他","n":5},{"title":"6 追東方提頭賴吒天王領乾闥婆眾印","file":"T21n1238","juan":1,"lb":"0182b16","type":"其他","n":6},{"title":"7 追南方毘流勒叉天王領鳩盤荼眾印","file":"T21n1238","juan":1,"lb":"0182b21","type":"其他","n":7},{"title":"8 追西方博叉天王領龍軍眾印","file":"T21n1238","juan":1,"lb":"0182b26","type":"其他","n":8},{"title":"9 追北方毘沙門天王領藥叉軍眾印","file":"T21n1238","juan":1,"lb":"0182c02","type":"其他","n":9},{"title":"10 集四天王所領四方鬼神藥叉羅剎八部鬼兵印","file":"T21n1238","juan":1,"lb":"0182c08","type":"其他","n":10},{"title":"11 集八部龍王軍眾印","file":"T21n1238","juan":1,"lb":"0182c14","type":"其他","n":11},{"title":"12 追百千天龍興雲致雨龍王印","file":"T21n1238","juan":1,"lb":"0182c19","type":"其他","n":12},{"title":"13 追日天子軍眾印","file":"T21n1238","juan":1,"lb":"0183a01","type":"其他","n":13},{"title":"14 追月天子眷屬印","file":"T21n1238","juan":1,"lb":"0183a06","type":"其他","n":14},{"title":"15 集一切火天魔兵令伏印","file":"T21n1238","juan":1,"lb":"0183a11","type":"其他","n":15},{"title":"16 追閻羅王五道大將軍牛頭兵眾印","file":"T21n1238","juan":1,"lb":"0183a15","type":"其他","n":16},{"title":"17 追阿修羅王鬥戰軍眾印","file":"T21n1238","juan":1,"lb":"0183a19","type":"其他","n":17},{"title":"18 追羅剎娑王軍兵能鬥戰者急來印","file":"T21n1238","juan":1,"lb":"0183a24","type":"其他","n":18},{"title":"19 追五方大力藥叉王軍眾印","file":"T21n1238","juan":1,"lb":"0183a28","type":"其他","n":19},{"title":"20 追阿利陀遮文荼印","file":"T21n1238","juan":1,"lb":"0183b03","type":"其他","n":20},{"title":"21 追毘那夜迦鬼神王咒印","file":"T21n1238","juan":1,"lb":"0183b07","type":"其他","n":21},{"title":"22 集摩醯首羅天王二十八部印","file":"T21n1238","juan":1,"lb":"0183b11","type":"其他","n":22},{"title":"23 阿吒薄拘大怒使金剛二十八部神降惡鬼印","file":"T21n1238","juan":1,"lb":"0183b15","type":"其他","n":23},{"title":"24 大將大悅會天龍鬼神自護身印","file":"T21n1238","juan":1,"lb":"0183b20","type":"其他","n":24},{"title":"25 百事不畏不被刀兵鬼神傷著衣甲印","file":"T21n1238","juan":1,"lb":"0183b22","type":"其他","n":25},{"title":"26 千輻輪降鬼印","file":"T21n1238","juan":1,"lb":"0183b26","type":"其他","n":26},{"title":"27 立身印","file":"T21n1238","juan":1,"lb":"0183b29","type":"其他","n":27},{"title":"28 刀印","file":"T21n1238","juan":1,"lb":"0183c05","type":"其他","n":28},{"title":"29 弓箭","file":"T21n1238","juan":1,"lb":"0183c09","type":"其他","n":29},{"title":"30 追般若不空罥索使者鬼神印","file":"T21n1238","juan":1,"lb":"0183c13","type":"其他","n":30}]},{"title":"2 大將使神散禁法","file":"T21n1238","juan":1,"lb":"0183c20","type":"其他","n":2}],"juan":[{"file":"T21n1238","juan":1,"lb":"0179b22","title":"第一"}]}]}