{"num_found":1,"time":0.001348643,"results":[{"mulu":[{"title":"第一卷","file":"T36n1740","juan":1,"lb":"1008c07","type":"其他"},{"title":"第二卷","file":"T36n1740","juan":1,"lb":"1008c10","type":"其他"},{"title":"第三卷","file":"T36n1740","juan":1,"lb":"1008c13","type":"其他"},{"title":"第四卷","file":"T36n1740","juan":1,"lb":"1008c16","type":"其他"},{"title":"第五卷","file":"T36n1740","juan":1,"lb":"1008c19","type":"其他"},{"title":"第六卷","file":"T36n1740","juan":1,"lb":"1008c22","type":"其他"},{"title":"第七卷","file":"T36n1740","juan":1,"lb":"1008c25","type":"其他"},{"title":"第八卷","file":"T36n1740","juan":1,"lb":"1008c28","type":"其他"},{"title":"第九卷","file":"T36n1740","juan":1,"lb":"1009a02","type":"其他"},{"title":"第十卷","file":"T36n1740","juan":1,"lb":"1009a04","type":"其他"},{"title":"第十一卷","file":"T36n1740","juan":1,"lb":"1009a07","type":"其他"},{"title":"第十二卷","file":"T36n1740","juan":1,"lb":"1009a10","type":"其他"},{"title":"第十三卷","file":"T36n1740","juan":1,"lb":"1009a13","type":"其他"},{"title":"第十四卷","file":"T36n1740","juan":1,"lb":"1009a16","type":"其他"},{"title":"第十五卷","file":"T36n1740","juan":1,"lb":"1009a19","type":"其他"},{"title":"第十六卷","file":"T36n1740","juan":1,"lb":"1009a22","type":"其他"},{"title":"第十七卷","file":"T36n1740","juan":1,"lb":"1009a25","type":"其他"},{"title":"第十八卷","file":"T36n1740","juan":1,"lb":"1009a28","type":"其他"},{"title":"第十九卷","file":"T36n1740","juan":1,"lb":"1009b02","type":"其他"},{"title":"第二十卷","file":"T36n1740","juan":1,"lb":"1009b05","type":"其他"},{"title":"第二十一卷","file":"T36n1740","juan":1,"lb":"1009b08","type":"其他"},{"title":"第二十二卷","file":"T36n1740","juan":1,"lb":"1009b11","type":"其他"},{"title":"第二十三卷","file":"T36n1740","juan":1,"lb":"1009b13","type":"其他"},{"title":"第二十四卷","file":"T36n1740","juan":1,"lb":"1009b16","type":"其他"},{"title":"第二十五卷","file":"T36n1740","juan":1,"lb":"1009b19","type":"其他"},{"title":"第二十六卷","file":"T36n1740","juan":1,"lb":"1009b22","type":"其他"},{"title":"第二十七卷","file":"T36n1740","juan":1,"lb":"1009b25","type":"其他"},{"title":"第二十八卷","file":"T36n1740","juan":1,"lb":"1009b28","type":"其他"},{"title":"第二十九卷","file":"T36n1740","juan":1,"lb":"1009c02","type":"其他"},{"title":"第三十卷","file":"T36n1740","juan":1,"lb":"1009c05","type":"其他"},{"title":"第三十一卷","file":"T36n1740","juan":1,"lb":"1009c08","type":"其他"},{"title":"第三十二卷","file":"T36n1740","juan":1,"lb":"1009c11","type":"其他"},{"title":"第三十三卷","file":"T36n1740","juan":1,"lb":"1009c14","type":"其他"},{"title":"第三十四卷","file":"T36n1740","juan":1,"lb":"1009c17","type":"其他"},{"title":"第三十五卷","file":"T36n1740","juan":1,"lb":"1009c20","type":"其他"},{"title":"第三十六卷","file":"T36n1740","juan":1,"lb":"1009c23","type":"其他"},{"title":"第三十七卷","file":"T36n1740","juan":1,"lb":"1009c26","type":"其他"},{"title":"第三十八卷","file":"T36n1740","juan":1,"lb":"1009c29","type":"其他"},{"title":"第三十九卷","file":"T36n1740","juan":1,"lb":"1010a03","type":"其他"},{"title":"第四十卷","file":"T36n1740","juan":1,"lb":"1010a06","type":"其他"},{"title":"第四十一卷","file":"T36n1740","juan":1,"lb":"1010a09","type":"其他"},{"title":"第四十二卷","file":"T36n1740","juan":1,"lb":"1010a12","type":"其他"},{"title":"第四十三卷","file":"T36n1740","juan":1,"lb":"1010a15","type":"其他"},{"title":"第四十四卷","file":"T36n1740","juan":1,"lb":"1010a18","type":"其他"},{"title":"第四十五卷","file":"T36n1740","juan":1,"lb":"1010a21","type":"其他"},{"title":"第四十六卷","file":"T36n1740","juan":1,"lb":"1010a24","type":"其他"},{"title":"第四十七卷","file":"T36n1740","juan":1,"lb":"1010a27","type":"其他"},{"title":"第四十八卷","file":"T36n1740","juan":1,"lb":"1010b01","type":"其他"},{"title":"第四十九卷","file":"T36n1740","juan":1,"lb":"1010b04","type":"其他"},{"title":"第五十卷","file":"T36n1740","juan":1,"lb":"1010b07","type":"其他"},{"title":"第五十一卷","file":"T36n1740","juan":1,"lb":"1010b10","type":"其他"},{"title":"第五十二卷","file":"T36n1740","juan":1,"lb":"1010b13","type":"其他"},{"title":"第五十三卷","file":"T36n1740","juan":1,"lb":"1010b16","type":"其他"},{"title":"第五十四卷","file":"T36n1740","juan":1,"lb":"1010b19","type":"其他"},{"title":"第五十五卷","file":"T36n1740","juan":1,"lb":"1010b22","type":"其他"},{"title":"第五十六卷","file":"T36n1740","juan":1,"lb":"1010b25","type":"其他"},{"title":"第五十七卷","file":"T36n1740","juan":1,"lb":"1010b28","type":"其他"},{"title":"第五十八卷","file":"T36n1740","juan":1,"lb":"1010c02","type":"其他"},{"title":"第五十九卷","file":"T36n1740","juan":1,"lb":"1010c05","type":"其他"},{"title":"第六十卷","file":"T36n1740","juan":1,"lb":"1010c08","type":"其他"},{"title":"第六十一卷","file":"T36n1740","juan":1,"lb":"1010c11","type":"其他"},{"title":"第六十二卷","file":"T36n1740","juan":1,"lb":"1010c14","type":"其他"},{"title":"第六十三卷","file":"T36n1740","juan":1,"lb":"1010c17","type":"其他"},{"title":"第六十四卷","file":"T36n1740","juan":1,"lb":"1010c20","type":"其他"},{"title":"第六十五卷","file":"T36n1740","juan":1,"lb":"1010c23","type":"其他"},{"title":"第六十六卷","file":"T36n1740","juan":1,"lb":"1010c26","type":"其他"},{"title":"第六十七卷","file":"T36n1740","juan":1,"lb":"1010c29","type":"其他"},{"title":"第六十八卷","file":"T36n1740","juan":1,"lb":"1011a03","type":"其他"},{"title":"第六十九卷","file":"T36n1740","juan":1,"lb":"1011a06","type":"其他"},{"title":"第七十卷","file":"T36n1740","juan":1,"lb":"1011a09","type":"其他"},{"title":"第七十一卷","file":"T36n1740","juan":1,"lb":"1011a12","type":"其他"},{"title":"第七十二卷","file":"T36n1740","juan":1,"lb":"1011a15","type":"其他"},{"title":"第七十三卷","file":"T36n1740","juan":1,"lb":"1011a18","type":"其他"},{"title":"第七十四卷","file":"T36n1740","juan":1,"lb":"1011a21","type":"其他"},{"title":"第七十五卷","file":"T36n1740","juan":1,"lb":"1011a24","type":"其他"},{"title":"第七十六卷","file":"T36n1740","juan":1,"lb":"1011a27","type":"其他"},{"title":"第七十七卷","file":"T36n1740","juan":1,"lb":"1011b01","type":"其他"},{"title":"第七十八卷","file":"T36n1740","juan":1,"lb":"1011b04","type":"其他"},{"title":"第七十九卷","file":"T36n1740","juan":1,"lb":"1011b07","type":"其他"},{"title":"第八十卷","file":"T36n1740","juan":1,"lb":"1011b10","type":"其他"}],"juan":[{"file":"T36n1740","juan":1,"lb":"1008c03","title":"第一"}]}]}