{"num_found":1,"time":0.000721124,"results":[{"mulu":[{"title":"1 分別界品","file":"T29n1561","juan":1,"lb":"0325a15","type":"品","n":1,"isFolder":true,"children":[{"title":"1","file":"T29n1561","juan":1,"lb":"0325a15","n":1},{"title":"2","file":"T29n1561","juan":2,"lb":"0326a04","n":2},{"title":"3","file":"T29n1561","juan":3,"lb":"0326b19","n":3},{"title":"4","file":"T29n1561","juan":4,"lb":"0326c24","n":4}]},{"title":"2 分別根品","file":"T29n1561","juan":5,"lb":"0327a27","type":"品","n":2}],"juan":[{"file":"T29n1561","juan":1,"lb":"0325a08","title":"第一"},{"file":"T29n1561","juan":2,"lb":"0326a04","title":"第二"},{"file":"T29n1561","juan":3,"lb":"0326b19","title":"第三"},{"file":"T29n1561","juan":4,"lb":"0326c24","title":"第四"},{"file":"T29n1561","juan":5,"lb":"0327a24","title":"第五"}]}]}