{"num_found":1,"time":0.000634552,"results":[{"mulu":[{"title":"1 序品","file":"T33n1707","juan":1,"lb":"0314b06","type":"品","n":1},{"title":"2 觀空品","file":"T33n1707","juan":1,"lb":"0323a09","type":"品","n":2},{"title":"3 菩薩教化品","file":"T33n1707","juan":2,"lb":"0328c05","type":"品","n":3},{"title":"4 二諦品","file":"T33n1707","juan":2,"lb":"0339a17","type":"品","n":4},{"title":"5 護國品","file":"T33n1707","juan":3,"lb":"0343c22","type":"品","n":5},{"title":"6 散華品","file":"T33n1707","juan":3,"lb":"0346c19","type":"品","n":6},{"title":"7 受持品","file":"T33n1707","juan":3,"lb":"0347c27","type":"品","n":7},{"title":"8 囑累品","file":"T33n1707","juan":3,"lb":"0357b26","type":"品","n":8}],"juan":[{"file":"T33n1707","juan":1,"lb":"0314b03","title":"上一"},{"file":"T33n1707","juan":1,"lb":"0321c19","title":"上二"},{"file":"T33n1707","juan":2,"lb":"0328c02","title":"中三"},{"file":"T33n1707","juan":2,"lb":"0335c14","title":"中四"},{"file":"T33n1707","juan":3,"lb":"0343c19","title":"下五"},{"file":"T33n1707","juan":3,"lb":"0351b23","title":"下六"}]}]}